videosdk/plugins/aws/__init__.py
videosdk/plugins/aws/aws_nova_sonic_api.py
videosdk/plugins/aws/tts.py
videosdk/plugins/aws/version.py
videosdk_plugins_aws-0.0.58.dist-info/METADATA
videosdk_plugins_aws-0.0.58.dist-info/WHEEL
videosdk_plugins_aws-0.0.58.dist-info/RECORD
