Metadata-Version: 2.4
Name: videosdk-plugins-aws
Version: 0.0.58
Summary: VideoSDK Agent Framework plugin for AWS
Author: videosdk
License-Expression: Apache-2.0
Keywords: ai,audio,aws,nova-sonic,video,videosdk
Classifier: Development Status :: 4 - Beta
Classifier: Intended Audience :: Developers
Classifier: Topic :: Communications :: Conferencing
Classifier: Topic :: Multimedia :: Sound/Audio
Classifier: Topic :: Multimedia :: Video
Classifier: Topic :: Scientific/Engineering :: Artificial Intelligence
Requires-Python: >=3.12
Requires-Dist: aws-sdk-bedrock-runtime
Requires-Dist: boto3
Requires-Dist: smithy-aws-core
Requires-Dist: videosdk-agents>=0.0.58
